[
  {
    "productId": 1,
    "productName": "Sarajevo",
    "productCode": "bvrk-71000",
    "releaseDate": "March 19, 1555",
    "description": "Burek in Sarajevo",
    "price": 1.50,
    "starRating": 4.9,
    "imageUrl": "assets/images/sarajevo.png"
  },
  {
    "productId": 2,
    "productName": "Tuzla",
    "productCode": "bvrk-75000",
    "releaseDate": "March 18, 1904",
    "description": "Burek in Tuzla",
    "price": 1.20,
    "starRating": 2,
    "imageUrl": "assets/images/tuzla.png"
  },
  {
    "productId": 3,
    "productName": "Mostar",
    "productCode": "bvrk-88000",
    "releaseDate": "May 21, 1801",
    "description": "Burek in Mostar",
    "price": 1.40,
    "starRating": 3,
    "imageUrl": "assets/images/mostar.png"
  },
  {
    "productId": 4,
    "productName": "Foca",
    "productCode": "bvrk-73301",
    "releaseDate": "May 15, 1656",
    "description": "Burek in Foča",
    "price": 99.99,
    "starRating": 5,
    "imageUrl": "assets/images/foca.png"
  },
  {
    "productId": 5,
    "productName": "Rogatica",
    "productCode": "bvrk-73220",
    "releaseDate": "October 15, 1723",
    "description": "Burek in Rogatica",
    "price": 1.95,
    "starRating": 4,
    "imageUrl": "assets/images/rogatica.png"
  }
]